epicsdev/__init__.py
epicsdev/epicsdev.py
epicsdev/multiadc.py
epicsdev-2.0.1.dist-info/METADATA
epicsdev-2.0.1.dist-info/WHEEL
epicsdev-2.0.1.dist-info/licenses/LICENSE
epicsdev-2.0.1.dist-info/RECORD
